_rpi_vl53l0x.cpython-35m-arm-linux-gnueabihf.so
rpi_vl53l0x/__init__.py
rpi_vl53l0x/vl53l0x.py
rpi_vl53l0x-0.0.2.dist-info/DESCRIPTION.rst
rpi_vl53l0x-0.0.2.dist-info/METADATA
rpi_vl53l0x-0.0.2.dist-info/RECORD
rpi_vl53l0x-0.0.2.dist-info/WHEEL
rpi_vl53l0x-0.0.2.dist-info/metadata.json
rpi_vl53l0x-0.0.2.dist-info/top_level.txt
