Metadata-Version: 2.0
Name: rpi-vl53l0x
Version: 0.0.2
Summary: Userspace Raspberry Pi VL53l0X library
Home-page: https://github.com/turmary/rpi-vl53l0x
Author: Peter Yang <turmary@126.com>
Author-email: turmary@126.com
License: MIT
Platform: UNKNOWN
